{"currentList":{"mega":[{"id":"AERODACTYL","form":"AERODACTYL_MEGA","costume":null,"assets":{"image":"https://raw.githubusercontent.com/pokemon-go-api/assets/main/Pokemon/pm142.fMEGA.icon.png","shinyImage":"https://raw.githubusercontent.com/pokemon-go-api/assets/main/Pokemon/pm142.fMEGA.s.icon.png"},"level":"mega","names":{"English":"Mega Aerodactyl","German":"Mega-Aerodactyl","French":"Méga-Ptéra","Italian":"MegaAerodactyl","Japanese":"メガプテラ","Korean":"메가프테라","Spanish":"Mega-Aerodactyl"},"shiny":true,"types":["Rock","Flying"],"counter":{"Electric":1.6,"Ice":1.6,"Rock":1.6,"Steel":1.6,"Water":1.6},"weather":["partlycloudy_day","windy"],"cpRange":[1515,1590],"cpRangeBoost":[1894,1988],"battleResult":{"easy":{"name":"easy","friendshipLevel":0,"pokemonLevel":20,"totalEstimator":1.7371078},"normal":{"name":"normal","friendshipLevel":3,"pokemonLevel":30,"totalEstimator":1.1064696},"hard":{"name":"hard","friendshipLevel":4,"pokemonLevel":40,"totalEstimator":0.98655754}}}],"lvl5":[{"id":"KYOGRE","form":"KYOGRE","costume":null,"assets":{"image":"https://raw.githubusercontent.com/pokemon-go-api/assets/main/Pokemon/pm382.icon.png","shinyImage":"https://raw.githubusercontent.com/pokemon-go-api/assets/main/Pokemon/pm382.s.icon.png"},"level":"lvl5","names":{"English":"Kyogre","German":"Kyogre","French":"Kyogre","Italian":"Kyogre","Japanese":"カイオーガ","Korean":"가이오가","Spanish":"Kyogre"},"shiny":true,"types":["Water"],"counter":{"Electric":1.6,"Grass":1.6},"weather":["rain"],"cpRange":[2260,2351],"cpRangeBoost":[2825,2939],"battleResult":{"easy":{"name":"easy","friendshipLevel":0,"pokemonLevel":20,"totalEstimator":3.7472084},"normal":{"name":"normal","friendshipLevel":3,"pokemonLevel":30,"totalEstimator":2.5459788},"hard":{"name":"hard","friendshipLevel":4,"pokemonLevel":40,"totalEstimator":2.2427628}}}],"lvl3":[{"id":"AMPHAROS","form":"AMPHAROS","costume":null,"assets":{"image":"https://raw.githubusercontent.com/pokemon-go-api/assets/main/Pokemon/pm181.icon.png","shinyImage":"https://raw.githubusercontent.com/pokemon-go-api/assets/main/Pokemon/pm181.s.icon.png"},"level":"lvl3","names":{"English":"Ampharos","German":"Ampharos","French":"Pharamp","Italian":"Ampharos","Japanese":"デンリュウ","Korean":"전룡","Spanish":"Ampharos"},"shiny":true,"types":["Electric"],"counter":{"Ground":1.6},"weather":["rain"],"cpRange":[1554,1630],"cpRangeBoost":[1943,2037],"battleResult":{"easy":{"name":"easy","friendshipLevel":0,"pokemonLevel":20,"totalEstimator":0.94329625},"normal":{"name":"normal","friendshipLevel":3,"pokemonLevel":30,"totalEstimator":0.68764657},"hard":{"name":"hard","friendshipLevel":4,"pokemonLevel":40,"totalEstimator":0.6103044}}},{"id":"SHIFTRY","form":"SHIFTRY","costume":null,"assets":{"image":"https://raw.githubusercontent.com/pokemon-go-api/assets/main/Pokemon/pm275.icon.png","shinyImage":"https://raw.githubusercontent.com/pokemon-go-api/assets/main/Pokemon/pm275.s.icon.png"},"level":"lvl3","names":{"English":"Shiftry","German":"Tengulist","French":"Tengalice","Italian":"Shiftry","Japanese":"ダーテング","Korean":"다탱구","Spanish":"Shiftry"},"shiny":true,"types":["Grass","Dark"],"counter":{"Bug":2.56,"Fairy":1.6,"Fighting":1.6,"Fire":1.6,"Flying":1.6,"Ice":1.6,"Poison":1.6},"weather":["sunny","fog"],"cpRange":[1263,1333],"cpRangeBoost":[1579,1666],"battleResult":{"easy":{"name":"easy","friendshipLevel":0,"pokemonLevel":20,"totalEstimator":0.4995761},"normal":{"name":"normal","friendshipLevel":3,"pokemonLevel":30,"totalEstimator":0.3604815},"hard":{"name":"hard","friendshipLevel":4,"pokemonLevel":40,"totalEstimator":0.3210439}}},{"id":"DHELMISE","form":"DHELMISE","costume":null,"assets":{"image":"https://raw.githubusercontent.com/pokemon-go-api/assets/main/Pokemon/pm781.icon.png","shinyImage":"https://raw.githubusercontent.com/pokemon-go-api/assets/main/Pokemon/pm781.s.icon.png"},"level":"lvl3","names":{"English":"Dhelmise","German":"Moruda","French":"Sinistrail","Italian":"Dhelmise","Japanese":"ダダリン","Korean":"타타륜","Spanish":"Dhelmise"},"shiny":true,"types":["Ghost","Grass"],"counter":{"Dark":1.6,"Fire":1.6,"Flying":1.6,"Ghost":1.6,"Ice":1.6},"weather":["sunny","fog"],"cpRange":[1608,1685],"cpRangeBoost":[2010,2107],"battleResult":{"easy":{"name":"easy","friendshipLevel":0,"pokemonLevel":20,"totalEstimator":0.8577798},"normal":{"name":"normal","friendshipLevel":3,"pokemonLevel":30,"totalEstimator":0.5697499},"hard":{"name":"hard","friendshipLevel":4,"pokemonLevel":40,"totalEstimator":0.48908636}}}],"lvl1":[{"id":"VULPIX","form":"VULPIX_ALOLA","costume":null,"assets":{"image":"https://raw.githubusercontent.com/pokemon-go-api/assets/main/Pokemon/pm37.fALOLA.icon.png","shinyImage":"https://raw.githubusercontent.com/pokemon-go-api/assets/main/Pokemon/pm37.fALOLA.s.icon.png"},"level":"lvl1","names":{"English":"Alolan Vulpix","German":"Alola-Vulpix","French":"Goupix d'Alola","Italian":"Vulpix di Alola","Japanese":"アローラ ロコン","Korean":"알로라 식스테일","Spanish":"Vulpix de Alola"},"shiny":true,"types":["Ice"],"counter":{"Fighting":1.6,"Fire":1.6,"Rock":1.6,"Steel":1.6},"weather":["snow"],"cpRange":[463,504],"cpRangeBoost":[579,631],"battleResult":{"easy":{"name":"easy","friendshipLevel":0,"pokemonLevel":20,"totalEstimator":0.069059126},"normal":{"name":"normal","friendshipLevel":3,"pokemonLevel":30,"totalEstimator":0.05631192},"hard":{"name":"hard","friendshipLevel":4,"pokemonLevel":40,"totalEstimator":0.053090736}}},{"id":"GOOMY","form":"GOOMY","costume":null,"assets":{"image":"https://raw.githubusercontent.com/pokemon-go-api/assets/main/Pokemon/pm704.icon.png","shinyImage":"https://raw.githubusercontent.com/pokemon-go-api/assets/main/Pokemon/pm704.s.icon.png"},"level":"lvl1","names":{"English":"Goomy","German":"Viscora","French":"Mucuscule","Italian":"Goomy","Japanese":"ヌメラ","Korean":"미끄메라","Spanish":"Goomy"},"shiny":true,"types":["Dragon"],"counter":{"Dragon":1.6,"Fairy":1.6,"Ice":1.6},"weather":["windy"],"cpRange":[514,557],"cpRangeBoost":[642,697],"battleResult":{"easy":{"name":"easy","friendshipLevel":0,"pokemonLevel":20,"totalEstimator":0.07448794},"normal":{"name":"normal","friendshipLevel":3,"pokemonLevel":30,"totalEstimator":0.05744551},"hard":{"name":"hard","friendshipLevel":4,"pokemonLevel":40,"totalEstimator":0.05374812}}},{"id":"ROOKIDEE","form":"ROOKIDEE","costume":null,"assets":{"image":"https://raw.githubusercontent.com/pokemon-go-api/assets/main/Pokemon/pm821.icon.png","shinyImage":"https://raw.githubusercontent.com/pokemon-go-api/assets/main/Pokemon/pm821.s.icon.png"},"level":"lvl1","names":{"English":"Rookidee","German":"Meikro","French":"Minisange","Italian":"Rookidee","Japanese":"ココガラ","Korean":"파라꼬","Spanish":"Rookidee"},"shiny":true,"types":["Flying"],"counter":{"Electric":1.6,"Ice":1.6,"Rock":1.6},"weather":["windy"],"cpRange":[344,380],"cpRangeBoost":[430,476],"battleResult":{"easy":{"name":"easy","friendshipLevel":0,"pokemonLevel":20,"totalEstimator":0.05273162},"normal":{"name":"normal","friendshipLevel":3,"pokemonLevel":30,"totalEstimator":0.047192603},"hard":{"name":"hard","friendshipLevel":4,"pokemonLevel":40,"totalEstimator":0.04146144}}},{"id":"SINISTEA","form":"SINISTEA","costume":null,"assets":{"image":"https://raw.githubusercontent.com/pokemon-go-api/assets/main/Pokemon/pm854.icon.png","shinyImage":"https://raw.githubusercontent.com/pokemon-go-api/assets/main/Pokemon/pm854.s.icon.png"},"level":"lvl1","names":{"English":"Sinistea","German":"Fatalitee","French":"Théffroi","Italian":"Sinistea","Japanese":"ヤバチャ","Korean":"데인차","Spanish":"Sinistea"},"shiny":true,"types":["Ghost"],"counter":{"Dark":1.6,"Ghost":1.6},"weather":["fog"],"cpRange":[603,650],"cpRangeBoost":[754,813],"battleResult":{"easy":{"name":"easy","friendshipLevel":0,"pokemonLevel":20,"totalEstimator":0.07044818},"normal":{"name":"normal","friendshipLevel":3,"pokemonLevel":30,"totalEstimator":0.056554466},"hard":{"name":"hard","friendshipLevel":4,"pokemonLevel":40,"totalEstimator":0.048497815}}}],"shadow_lvl5":[{"id":"LATIOS","form":"LATIOS","costume":null,"assets":{"image":"https://raw.githubusercontent.com/pokemon-go-api/assets/main/Pokemon/pm381.icon.png","shinyImage":"https://raw.githubusercontent.com/pokemon-go-api/assets/main/Pokemon/pm381.s.icon.png"},"level":"shadow_lvl5","names":{"English":"Latios","German":"Latios","French":"Latios","Italian":"Latios","Japanese":"ラティオス","Korean":"라티오스","Spanish":"Latios"},"shiny":true,"types":["Dragon","Psychic"],"counter":{"Bug":1.6,"Dark":1.6,"Dragon":1.6,"Fairy":1.6,"Ghost":1.6,"Ice":1.6},"weather":["windy"],"cpRange":[2090,2178],"cpRangeBoost":[2613,2723],"battleResult":{"easy":{"name":"easy","friendshipLevel":0,"pokemonLevel":20,"totalEstimator":4.744968},"normal":{"name":"normal","friendshipLevel":3,"pokemonLevel":30,"totalEstimator":3.16198},"hard":{"name":"hard","friendshipLevel":4,"pokemonLevel":40,"totalEstimator":2.7562847}}}],"shadow_lvl3":[{"id":"MAROWAK","form":"MAROWAK_ALOLA","costume":null,"assets":{"image":"https://raw.githubusercontent.com/pokemon-go-api/assets/main/Pokemon/pm105.fALOLA.icon.png","shinyImage":"https://raw.githubusercontent.com/pokemon-go-api/assets/main/Pokemon/pm105.fALOLA.s.icon.png"},"level":"shadow_lvl3","names":{"English":"Alolan Marowak","German":"Alola-Knogga","French":"Ossatueur d'Alola","Italian":"Marowak di Alola","Japanese":"アローラ ガラガラ","Korean":"알로라 텅구리","Spanish":"Marowak de Alola"},"shiny":true,"types":["Fire","Ghost"],"counter":{"Dark":1.6,"Ghost":1.6,"Ground":1.6,"Rock":1.6,"Water":1.6},"weather":["sunny","fog"],"cpRange":[988,1048],"cpRangeBoost":[1235,1311],"battleResult":{"easy":{"name":"easy","friendshipLevel":0,"pokemonLevel":20,"totalEstimator":0.9526157},"normal":{"name":"normal","friendshipLevel":3,"pokemonLevel":30,"totalEstimator":0.64043635},"hard":{"name":"hard","friendshipLevel":4,"pokemonLevel":40,"totalEstimator":0.55435824}}},{"id":"LAPRAS","form":"LAPRAS","costume":null,"assets":{"image":"https://raw.githubusercontent.com/pokemon-go-api/assets/main/Pokemon/pm131.icon.png","shinyImage":"https://raw.githubusercontent.com/pokemon-go-api/assets/main/Pokemon/pm131.s.icon.png"},"level":"shadow_lvl3","names":{"English":"Lapras","German":"Lapras","French":"Lokhlass","Italian":"Lapras","Japanese":"ラプラス","Korean":"라프라스","Spanish":"Lapras"},"shiny":true,"types":["Water","Ice"],"counter":{"Electric":1.6,"Fighting":1.6,"Grass":1.6,"Rock":1.6},"weather":["rain","snow"],"cpRange":[1435,1509],"cpRangeBoost":[1794,1886],"battleResult":{"easy":{"name":"easy","friendshipLevel":0,"pokemonLevel":20,"totalEstimator":1.6681165},"normal":{"name":"normal","friendshipLevel":3,"pokemonLevel":30,"totalEstimator":1.1280514},"hard":{"name":"hard","friendshipLevel":4,"pokemonLevel":40,"totalEstimator":0.97898364}}},{"id":"STANTLER","form":"STANTLER","costume":null,"assets":{"image":"https://raw.githubusercontent.com/pokemon-go-api/assets/main/Pokemon/pm234.icon.png","shinyImage":"https://raw.githubusercontent.com/pokemon-go-api/assets/main/Pokemon/pm234.s.icon.png"},"level":"shadow_lvl3","names":{"English":"Stantler","German":"Damhirplex","French":"Cerfrousse","Italian":"Stantler","Japanese":"オドシシ","Korean":"노라키","Spanish":"Stantler"},"shiny":true,"types":["Normal"],"counter":{"Fighting":1.6},"weather":["partlycloudy_day"],"cpRange":[1170,1236],"cpRangeBoost":[1463,1546],"battleResult":{"easy":{"name":"easy","friendshipLevel":0,"pokemonLevel":20,"totalEstimator":1.2948586},"normal":{"name":"normal","friendshipLevel":3,"pokemonLevel":30,"totalEstimator":0.8783996},"hard":{"name":"hard","friendshipLevel":4,"pokemonLevel":40,"totalEstimator":0.76305556}}}],"shadow_lvl1":[{"id":"DRATINI","form":"DRATINI","costume":null,"assets":{"image":"https://raw.githubusercontent.com/pokemon-go-api/assets/main/Pokemon/pm147.icon.png","shinyImage":"https://raw.githubusercontent.com/pokemon-go-api/assets/main/Pokemon/pm147.s.icon.png"},"level":"shadow_lvl1","names":{"English":"Dratini","German":"Dratini","French":"Minidraco","Italian":"Dratini","Japanese":"ミニリュウ","Korean":"미뇽","Spanish":"Dratini"},"shiny":true,"types":["Dragon"],"counter":{"Dragon":1.6,"Fairy":1.6,"Ice":1.6},"weather":["windy"],"cpRange":[529,574],"cpRangeBoost":[661,717],"battleResult":{"easy":{"name":"easy","friendshipLevel":0,"pokemonLevel":20,"totalEstimator":0.052277733},"normal":{"name":"normal","friendshipLevel":3,"pokemonLevel":30,"totalEstimator":0.042601462},"hard":{"name":"hard","friendshipLevel":4,"pokemonLevel":40,"totalEstimator":0.038877744}}},{"id":"GLIGAR","form":"GLIGAR","costume":null,"assets":{"image":"https://raw.githubusercontent.com/pokemon-go-api/assets/main/Pokemon/pm207.icon.png","shinyImage":"https://raw.githubusercontent.com/pokemon-go-api/assets/main/Pokemon/pm207.s.icon.png"},"level":"shadow_lvl1","names":{"English":"Gligar","German":"Skorgla","French":"Scorplane","Italian":"Gligar","Japanese":"グライガー","Korean":"글라이거","Spanish":"Gligar"},"shiny":true,"types":["Ground","Flying"],"counter":{"Ice":2.56,"Water":1.6},"weather":["sunny","windy"],"cpRange":[1000,1061],"cpRangeBoost":[1250,1326],"battleResult":{"easy":{"name":"easy","friendshipLevel":0,"pokemonLevel":20,"totalEstimator":0.07509016},"normal":{"name":"normal","friendshipLevel":3,"pokemonLevel":30,"totalEstimator":0.05989052},"hard":{"name":"hard","friendshipLevel":4,"pokemonLevel":40,"totalEstimator":0.05235632}}},{"id":"CACNEA","form":"CACNEA","costume":null,"assets":{"image":"https://raw.githubusercontent.com/pokemon-go-api/assets/main/Pokemon/pm331.icon.png","shinyImage":"https://raw.githubusercontent.com/pokemon-go-api/assets/main/Pokemon/pm331.s.icon.png"},"level":"shadow_lvl1","names":{"English":"Cacnea","German":"Tuska","French":"Cacnea","Italian":"Cacnea","Japanese":"サボネア","Korean":"선인왕","Spanish":"Cacnea"},"shiny":true,"types":["Grass"],"counter":{"Bug":1.6,"Fire":1.6,"Flying":1.6,"Ice":1.6,"Poison":1.6},"weather":["sunny"],"cpRange":[658,709],"cpRangeBoost":[822,887],"battleResult":{"easy":{"name":"easy","friendshipLevel":0,"pokemonLevel":20,"totalEstimator":0.047332022},"normal":{"name":"normal","friendshipLevel":3,"pokemonLevel":30,"totalEstimator":0.03704082},"hard":{"name":"hard","friendshipLevel":4,"pokemonLevel":40,"totalEstimator":0.03424759}}},{"id":"JOLTIK","form":"JOLTIK","costume":null,"assets":{"image":"https://raw.githubusercontent.com/pokemon-go-api/assets/main/Pokemon/pm595.icon.png","shinyImage":"https://raw.githubusercontent.com/pokemon-go-api/assets/main/Pokemon/pm595.s.icon.png"},"level":"shadow_lvl1","names":{"English":"Joltik","German":"Wattzapf","French":"Statitik","Italian":"Joltik","Japanese":"バチュル","Korean":"파쪼옥","Spanish":"Joltik"},"shiny":true,"types":["Bug","Electric"],"counter":{"Fire":1.6,"Rock":1.6},"weather":["rain"],"cpRange":[539,584],"cpRangeBoost":[674,730],"battleResult":{"easy":{"name":"easy","friendshipLevel":0,"pokemonLevel":20,"totalEstimator":0.06365693},"normal":{"name":"normal","friendshipLevel":3,"pokemonLevel":30,"totalEstimator":0.047364008},"hard":{"name":"hard","friendshipLevel":4,"pokemonLevel":40,"totalEstimator":0.044304956}}}]},"graphics":{"German":{"svg":"/api/graphics/German/default.svg","png":"/api/graphics/German/default.png","sha512":"96801bade5baa15ccc5a3876106810a7f627a439e6e6f29d9e23d0107946d9720b2896bcc55cd4f18d78bafe5cbc83f305adc5e81d6821a9accf77e489463708"},"English":{"svg":"/api/graphics/English/default.svg","png":"/api/graphics/English/default.png","sha512":"34bbee179d77fed95ffd14f27da5b1cc45f8cc09cd34eb5e3f4bdbb9b451a7ad12089e6021800b0c5ca7b3cdbcb1555da90e471b59e5fc621eebaf96b72b179c"}}}